{
  "workbench.colorTheme": "Dracula",
  "workbench.iconTheme": "material-icon-theme",
  "workbench.colorCustomizations": {
    "editor.background": "#0b080e",
    "terminal.background": "#0b090e"
  },
  "breadcrumbs.enabled": true,
  "editor.fontFamily": "Operator Mono Lig",
  "editor.fontLigatures": true,
  "editor.fontSize": 13,
  "editor.wordWrapColumn": 120,
  "editor.rulers": [
    80,
    120
  ],
  "editor.minimap.enabled": true,
  "editor.renderControlCharacters": false,
  "editor.tokenColorCustomizations": {
    "textMateRules": [
      {
        "scope": [
          //following will be in ligatures
          "comment",
          "entity.name.type.class", //class names
          "entity.name.type.className",
          "keyword", //import, export, return…
          "storage",
          "constant", //String, Number, Boolean…, this, super
          "storage.type.function",
          "storage.modifier", //static keyword
          "storage.type.class", //class keyword
          "entity.other.attribute-name",
          "entity.other.attribute-name.html"
        ],
        "settings": {
          "fontStyle": "italic"
        }
      },
      {
        "scope": [
          //following will be excluded from italics (VSCode has some defaults for italics)
          "invalid",
          "keyword.operator",
          "constant.numeric.css",
          "keyword.other.unit.px.css",
          "constant.numeric.decimal.js",
          "constant.numeric.json"
        ],
        "settings": {
          "fontStyle": ""
        }
      }
    ]
  },
  "terminal.integrated.fontFamily": "Operator Mono Lig",
  "terminal.integrated.shell.windows": "C:\\WINDOWS\\System32\\wsl.exe",
  "files.associations": {
    "*.js": "javascriptreact"
  }
}
